aet.consumer-3.12.0-py3.8-nspkg.pth
aet/api.py
aet/consumer.py
aet/exceptions.py
aet/helpers.py
aet/job.py
aet/jsonpath.py
aet/kafka.py
aet/kafka_utils.py
aet/logger.py
aet/resource.py
aet/settings.py
tests/__init__.py
tests/test_sdk.py
tests/assets/__init__.py
tests/assets/schemas.py
aet.consumer-3.12.0.dist-info/LICENSE
aet.consumer-3.12.0.dist-info/METADATA
aet.consumer-3.12.0.dist-info/WHEEL
aet.consumer-3.12.0.dist-info/namespace_packages.txt
aet.consumer-3.12.0.dist-info/top_level.txt
aet.consumer-3.12.0.dist-info/RECORD
