Metadata-Version: 2.1
Name: aet.consumer
Version: 3.12.0
Summary: A library to consume messages from Kafka with added functionality based on         Aether's schema metadata     
Home-page: https://github.com/eHealthAfrica/aether-consumer-sdk
Author: Shawn Sarwar
Author-email: shawn.sarwar@ehealthafrica.org
License: Apache2 License
Keywords: aet,aether,kafka,consumer
Platform: UNKNOWN
Classifier: Development Status :: 4 - Beta
Classifier: Intended Audience :: Developers
Classifier: License :: OSI Approved :: Apache Software License
Classifier: Natural Language :: English
Classifier: Operating System :: OS Independent
Classifier: Programming Language :: Python :: 3 :: Only
Classifier: Topic :: Software Development :: Libraries :: Python Modules
Requires-Python: >=3.6
License-File: LICENSE
Requires-Dist: aether.python
Requires-Dist: confluent-kafka
Requires-Dist: flask
Requires-Dist: jsonpath-ng
Requires-Dist: jsonschema
Requires-Dist: kafka-python
Requires-Dist: redis
Requires-Dist: requests
Requires-Dist: spavro
Requires-Dist: webtest
